surf_report/__init__.py
surf_report/main.py
surf_report/providers/surfline/__init__.py
surf_report/providers/surfline/models.py
surf_report/providers/surfline/processing.py
surf_report/providers/surfline/surfline.py
surf_report/providers/surfline/ui.py
surf_report/utils/helpers.py
surf_report/utils/logger.py
surf_report/utils/pager.py
surf_report/utils/user_agent.py
surfreport-0.1.0.dist-info/licenses/LICENSE
surfreport-0.1.0.dist-info/METADATA
surfreport-0.1.0.dist-info/WHEEL
surfreport-0.1.0.dist-info/entry_points.txt
surfreport-0.1.0.dist-info/top_level.txt
surfreport-0.1.0.dist-info/RECORD
