Metadata-Version: 2.4
Name: surfreport
Version: 0.1.0
Summary: Get the surf report in your terminal
Author: jtabke
License: MIT
Project-URL: homepage, https://github.com/jtabke/surfreport
Project-URL: repository, https://github.com/jtabke/surfreport
Keywords: surf,surf report,weather,ocean
Classifier: Programming Language :: Python :: 3
Classifier: License :: OSI Approved :: MIT License
Requires-Python: >=3.10
License-File: LICENSE
Requires-Dist: requests
Provides-Extra: dev
Requires-Dist: ruff; extra == "dev"
Requires-Dist: pyright; extra == "dev"
Requires-Dist: pytest; extra == "dev"
Provides-Extra: build
Requires-Dist: build; extra == "build"
Requires-Dist: twine; extra == "build"
Requires-Dist: commitizen; extra == "build"
Dynamic: license-file
